cochl/__init__.py
cochl/_openapi_client/__init__.py
cochl/_openapi_client/api_client.py
cochl/_openapi_client/api_response.py
cochl/_openapi_client/configuration.py
cochl/_openapi_client/exceptions.py
cochl/_openapi_client/py.typed
cochl/_openapi_client/rest.py
cochl/_openapi_client/api/__init__.py
cochl/_openapi_client/api/audio_session_api.py
cochl/_openapi_client/models/__init__.py
cochl/_openapi_client/models/audio_chunk.py
cochl/_openapi_client/models/create_session.py
cochl/_openapi_client/models/created_session.py
cochl/_openapi_client/models/generic_error.py
cochl/_openapi_client/models/official_tag.py
cochl/_openapi_client/models/page.py
cochl/_openapi_client/models/predict_request.py
cochl/_openapi_client/models/predict_response.py
cochl/_openapi_client/models/sense.py
cochl/_openapi_client/models/sense_event.py
cochl/_openapi_client/models/sense_event_tag.py
cochl/_openapi_client/models/session_refs.py
cochl/_openapi_client/models/session_result.py
cochl/_openapi_client/models/session_status.py
cochl/_openapi_client/models/session_type.py
cochl/_openapi_client/models/update_session.py
cochl/experimental/__init__.py
cochl/sense/__init__.py
cochl/sense/client.py
cochl/sense/config.py
cochl/sense/custom_sound.py
cochl/sense/event_detection.py
cochl/sense/exceptions.py
cochl/sense/http_request.py
cochl/sense/requirements.txt
cochl/sense/result.py
cochl/sense/speaker_recognition.py
cochl/sense/version.py
cochl-1.0.13.dist-info/METADATA
cochl-1.0.13.dist-info/WHEEL
cochl-1.0.13.dist-info/licenses/LICENSE
cochl-1.0.13.dist-info/RECORD
