Metadata-Version: 2.4
Name: cochl
Version: 1.0.13
Summary: Cochl Sense
Project-URL: Homepage, https://github.com/cochlearai/cochl-sense-py
Project-URL: Issues, https://github.com/cochlearai/cochl-sense-py/issues
Author-email: Cochl <support@cochl.ai>
License-File: LICENSE
Classifier: License :: OSI Approved :: MIT License
Classifier: Operating System :: OS Independent
Classifier: Programming Language :: Python :: 3
Requires-Python: >=3.10
Requires-Dist: pydantic>=2.11.7
Requires-Dist: python-dateutil>=2.9.0.post0
Requires-Dist: soundfile
Requires-Dist: urllib3>=2.4.0
